README.rst
setup.py
lahman_update/__init__.py
lahman_update/argparser.py
lahman_update/db_tools.py
lahman_update/lahman_update.py
lahman_update/scraper.py
lahman_updater.egg-info/PKG-INFO
lahman_updater.egg-info/SOURCES.txt
lahman_updater.egg-info/dependency_links.txt
lahman_updater.egg-info/requires.txt
lahman_updater.egg-info/top_level.txt
utils/__init__.py
utils/dataMover.py