Metadata-Version: 1.0
Name: lahman-updater
Version: 1.0.0
Summary: Update lahman database
Home-page: https://github.com/aitchslash
Author: Benjamin Field
Author-email: benjamin.field@gmail.com
License: MIT License
